LogTag/__init__.py
LogTag/logtag.py
logtag-2.2.0.dist-info/LICENSE
logtag-2.2.0.dist-info/METADATA
logtag-2.2.0.dist-info/WHEEL
logtag-2.2.0.dist-info/entry_points.txt
logtag-2.2.0.dist-info/top_level.txt
logtag-2.2.0.dist-info/RECORD
